wbi/__init__.py
wbi/testing/__init__.py
wbi/testing/tests.py
wbi/wavelet_regularization/__init__.py
wbi/wavelet_regularization/wavelet_regularization.py
wabi-0.1.1.dist-info/LICENSE
wabi-0.1.1.dist-info/METADATA
wabi-0.1.1.dist-info/WHEEL
wabi-0.1.1.dist-info/top_level.txt
wabi-0.1.1.dist-info/RECORD
