Metadata-Version: 2.1
Name: wabi
Version: 0.1.1
Summary: Wavelet-based regularization scheme 1D inversion
Home-page: https://github.com/WouterDls/1D-wavelet-based-inversion
Author: Wouter Deleersnyder
Author-email: Wouter.Deleersnyder@kuleuven.be
License: BSD-3
Classifier: Intended Audience :: Science/Research
Classifier: License :: OSI Approved
Classifier: Programming Language :: Python
Classifier: Topic :: Scientific/Engineering
Classifier: Operating System :: Microsoft :: Windows
Classifier: Operating System :: Unix
Classifier: Operating System :: MacOS
Classifier: Programming Language :: Python :: 3.7
Classifier: Programming Language :: Python :: 3.8
Classifier: Programming Language :: Python :: 3.9
Requires-Python: >=3.7
License-File: LICENSE
Requires-Dist: numpy
Requires-Dist: scipy
Requires-Dist: cython
Requires-Dist: simpeg
Requires-Dist: PyWavelets
